Workbook

Sheet Vagas
A1: Título | B1: Empresa | C1: Fonte | D1: Local | E1: Tipo de contratação | F1: Modelo de trabalho | G1: Nível da vaga | H1: Clusters identificados | I1: Vaga afirmativa | J1: Data de publicação | K1: Link | L1: Resumo | M1: Post formatado
A2: Software Engineer, AI Coding Tasks | B2: Askable | C2: Remotive | D2: Worldwide | E2: Não identificado | F2: Remoto | G2: Professional/Experienced | H2: Dev, IA | I2: Não | J2: 2026-10-17 | K2: Abrir vaga | L2: Software Engineer, AI Coding Tasks We're looking for experienced software engineers to build AI coding tasks from a codebase they know well. US$1,000 per task, and you can do as many tasks as you want. You turn a real change from a repository you know into a task that today's best AI coding models struggle with: hard for the models, but fair for a skilled engineer. Your tasks are used to measure and train AI coding models. Remote, any location. US$1,000 per task that passes review. Minimum of one task a week, about 10 hours a week. How it works Apply. Complete a short screener interview and upload your resume. Propose. Once you're selected, pick a change from a repository you know and submit a short proposal. We approve it or suggest a better candidate. Build. In our platform, set up the repository as it was before the change, then write the brief, the correct solution and the grading checks. Stress-test. Try lazy, incorrect and shortcut solutions and make sure your checks catch them. Model testing. Run your task against leading AI models until strong models often fail but a skilled engineer can clearly solve it. Review. A reviewer checks your task and you revise it. Most tasks take more than one round. Next task. Once your task is accepted, start another. Requirements 2+ years of professional software engineering Code merged into a public open-source repository, ideally one you know well. A private codebase you own may also qualify (not employer or client code) Strong in at least one of Python, TypeScript, Go, Rust, Java or C++ Solid with Docker, Linux, Git and automated testing Regular use of an AI coding tool Experience writing tests, rubrics or evaluation criteria, ideally for AI models You can explain a change clearly and concisely, in your own words At least 10 hours a week, starting now A secure personal or work computer (no public or shared machines) Nice to have Deep expertise in one area, such as databases, compilers, distributed systems, security or in... | M2: 💼 Software Engineer, AI Coding Tasks 🏢 Askable 📍 Worldwide · Remoto 🎯 Professional/Experienced 🧩 Área: Dev, IA We're looking for experienced software engineers to build AI coding tasks from a codebase they know well. US$1,000 per task, and you can do as many tasks as you want. You turn a real change from a repository you know into a task that today's best AI coding models struggle with: hard for the models, but fair for a skilled engineer. 🔗 Candidate-se: https://remotive.com/remote-jobs/software-development/software-engineer-ai-coding-tasks-2091158 Fonte: Remotive #Vagas #TalentLab #Desenvolvimento #InteligenciaArtificial
A3: Tech Lead Full-Stack Rails Engineer | B3: Mitre Media | C3: Remotive | D3: USA, Canada, USA timezones | E3: Não identificado | F3: Híbrido, Remoto | G3: Leadership | H3: IA, Tech Business & Liderança | I3: Não | J3: 2026-10-14 | K3: Abrir vaga | L3: Tech Lead Full-Stack Rails Engineer About Mitre Media Mitre Media is redefining FinTech with AI-driven tools that empower millions of investors. Our portfolio, including Dividend.com and MutualFunds.com, leverages LLMs to deliver novel data insights and visually rich user experiences. For over a decade, we’ve served individual investors, financial advisors, and top asset managers like BlackRock and Vanguard through our premium data, tools, and advertising solutions. Join our lean, entrepreneurial team to shape the future of AI-powered investing from your location ±3 hours from Eastern Time. Our users are deeply engaged, spending over 5 minutes per visit with a bounce rate below 10%, researching investments across hundreds of different categories. With 40 million brokerage accounts in the U.S., we take pride in building tools that make a real impact, fostering a culture of trust, innovation, and dynamism. If you’re passionate about financial technology and AI, we’d love to connect! About the Role As a Full-Stack Rails Tech Lead, you’ll architect and implement LLM-powered web applications within our microservices-based Rails 8 platform. Reporting directly to our CTO, you’ll collaborate with a small, high-impact team to deliver user experiences across Dividend.com, MutualFunds.com and other brands within our portfolio. This role combines expert Ruby on Rails skills with AI integration expertise, requiring you to leverage LLMs in your development workflow, state management and user interactions. You’ll work in a remote-first hybrid environment, which encourages in person collaboration, using ShapeUp to manage projects that trade-off on-time delivery for de-scoped outcomes. As a technical leader, you'll have a seat at the table shaping system architecture, implementing core features all while embracing an entrepreneurial mindset and a “get things done” mentality. Responsibilities Architect and maintain Rails applications (Rails 8) Integrate LLMs into our microservices... | M3: 💼 Tech Lead Full-Stack Rails Engineer 🏢 Mitre Media 📍 USA, Canada, USA timezones · Híbrido, Remoto 🎯 Leadership 🧩 Área: IA, Tech Business & Liderança About Mitre Media Mitre Media is redefining FinTech with AI-driven tools that empower millions of investors. Our portfolio, including Dividend.com and MutualFunds.com, leverages LLMs to deliver novel data insights and visually rich user experiences. 🔗 Candidate-se: https://remotive.com/remote-jobs/software-development/tech-lead-full-stack-rails-engineer-2069746 Fonte: Remotive #Vagas #TalentLab #InteligenciaArtificial #GestaoDeTI
A4: Remote Office Assistant | B4: Coalition Technologies | C4: Remotive | D4: Worldwide | E4: Não identificado | F4: Remoto | G4: Early Career | H4: Não identificado | I4: Não | J4: 2026-10-11 | K4: Abrir vaga | L4: Remote Office Assistant Coalition Technologies is seeking a reliable, detail-oriented, and highly organized Remote Office Assistant to support administrative, bookkeeping, billing, reporting, data entry, and internal operations tasks. This role is ideal for someone with strong communication skills, discretion, attention to detail, and a willingness to learn and grow within a fast-paced remote work environment. As an Office Assistant, you will help support daily administrative operations, assist with entry-level bookkeeping, organize client documents, support internal reporting, and help maintain accurate company records. This position offers strong growth potential for the right candidate, including opportunities for advancement within the Accounting team or other departments. We are looking for talented and diligent candidates who perform well on our skills assessments. Strong skills test performance may be considered even if a candidate does not meet every preferred experience or educational background requirement. Why Join Coalition Technologies? Coalition Technologies is committed to delivering high-quality work for our clients while providing our team with a fun, thriving, innovative, and growth-focused work environment. We offer: 100% remote work with a company that has supported remote team members for more than a decade Competitive profit-sharing bonus plan, with up to 50% of company profits paid to full-time employees each month Competitive Paid Time Off plan that supports work-life balance Subsidized gym memberships Medical, dental, vision, and life insurance packages for eligible US-based team members International Health Insurance Reimbursement Program for eligible international team members Device upgrade and learning reimbursement programs Career development plans with clearly defined goals and rewards Additional job-specific incentives and bonuses Office Assistant Responsibilities As an Office Assistant, your duties will include: Answering phones a... | M4: 💼 Remote Office Assistant 🏢 Coalition Technologies 📍 Worldwide · Remoto 🎯 Early Career Coalition Technologies is seeking a reliable, detail-oriented, and highly organized Remote Office Assistant to support administrative, bookkeeping, billing, reporting, data entry, and internal operations tasks. 🔗 Candidate-se: https://remotive.com/remote-jobs/marketing/remote-office-assistant-1680495 Fonte: Remotive #Vagas #TalentLab
A5: Inside Sales Contractor | B5: Credit Wellness, LLC | C5: Remotive | D5: Worldwide | E5: Não identificado | F5: Remoto | G5: Leadership | H5: Não identificado | I5: Não | J5: 2026-10-08 | K5: Abrir vaga | L5: Inside Sales Contractor About Us We are a financial services start up focusing on helping to improve consumer credit profiles. We are currently seeking KPI driven sales representatives looking to earn up to 45K in their first year while working remotely. We offer comprehensive training and continuous sales coaching to help you meet your financial goals. During our training period we offer a guaranteed training stipend while our trainees are acclimating to the position (*see weekly pay below). If you are a seasoned sales professional looking for the autonomy of a remote position combined with great compensation, we want to hear from you! Compensation Structure This role is 100% commission-based , which means your earning potential is unlimited. In addition, we regularly offer competitive performance-based bonuses to reward hard work and results. Training Period (Weeks 1–4) We invest in your success and want to make sure you’re supported as you get up to speed: Week 1: Commission-only (a chance to start earning right away while learning the ropes). Weeks 2–4: Guaranteed training stipend of $500 USD total – or your commission if it’s higher. You’ll always receive whichever amount benefits you most. Week 0: Unpaid Week 1: $100 guaranteed minimum Week 2: $150 guaranteed minimum Week 3: $250 guaranteed minimum By the end of training, you’ll have the skills to maximize commissions, with the safety net of a guaranteed base during your ramp-up period. Post Training Period: Average first year OTE: 25K-35K (US) Annually Top Rep first year OTE: 35K-45K (US) Annually *The above is the average pay you can expect, however, there is unlimited earning potential for those who are financially motivated top performers looking to exceed sales targets. What will you be doing? Educating inbound callers on their credit standing by providing consultations with the goal of enrolling them in one of our services should they be a good fit. We are looking for team members who are: Tech savvy ... | M5: 💼 Inside Sales Contractor 🏢 Credit Wellness, LLC 📍 Worldwide · Remoto 🎯 Leadership About Us We are a financial services start up focusing on helping to improve consumer credit profiles. We are currently seeking KPI driven sales representatives looking to earn up to 45K in their first year while working remotely. We offer comprehensive training and continuous sales coaching to help you meet your financial goals. 🔗 Candidate-se: https://remotive.com/remote-jobs/sales/inside-sales-contractor-2086540 Fonte: Remotive #Vagas #TalentLab
A6: Tier III Service Desk Engineer | B6: Unio Digital | C6: Remotive | D6: Worldwide | E6: Não identificado | F6: Remoto | G6: Leadership | H6: Cloud & Infraestrutura | I6: Não | J6: 2026-10-07 | K6: Abrir vaga | L6: Tier III Service Desk Engineer Unió Digital is an Arizona-based managed service provider (MSP) delivering Managed IT Services, Low Voltage Cabling, Access Control, Video Surveillance, and Intrusion Services. We believe technology should be intuitive, not intimidating. We are looking for an experienced Tier 3 Service Desk Technician with exceptional problem-solving skills. You will serve as the escalation point within the team, resolving complex technical issues while also leading client onboarding and project initiatives. You are expected to be involved in direct end-user support when required. If you have a passion for ensuring top-quality user support and thrive in a collaborative environment, this role is for you. Duties · Lead and support our helpdesk environment for managed service clients · Coordinate and manage client projects, acting as a bridge between the technical team and the client to ensure project success · Provide above and beyond support to our clients and respond to queries for technical assistance in person, via phone, or electronically as required · Provide training and support to clients during the onboarding process to ensure they understand how to effectively use their new IT systems and services. · Develop project plans for client onboarding and standardization projects, outlining tasks, resources required, and estimated timelines · Install, configure, diagnose, test and resolve technical hardware and software issues · Maintain and update written client and process documentation to ensure effective knowledge management · Provide mentorship and guidance to Tier I and Tier II service desk technicians, fostering a collaborative and knowledgeable team environment · Contribute to the development and improvement of IT service management processes and practices · Evaluate and anticipate IT trends and recommend strategies and implement improvement initiatives Our Technology Stack · Helpdesk / Ticketing – HaloPSA · Documentation – Hudu · RMM – Intu... | M6: 💼 Tier III Service Desk Engineer 🏢 Unio Digital 📍 Worldwide · Remoto 🎯 Leadership 🧩 Área: Cloud & Infraestrutura Unió Digital is an Arizona-based managed service provider (MSP) delivering Managed IT Services, Low Voltage Cabling, Access Control, Video Surveillance, and Intrusion Services. We believe technology should be intuitive, not intimidating. We are looking for an experienced Tier 3 Service Desk Technician with exceptional problem-solving skills. 🔗 Candidate-se: https://remotive.com/remote-jobs/information-technology/tier-iii-service-desk-engineer-2091045 Fonte: Remotive #Vagas #TalentLab #Cloud
A7: Freelance Writer | B7: IAPWE | C7: Remotive | D7: Worldwide | E7: Não identificado | F7: Remoto | G7: Advanced/Expert | H7: Não identificado | I7: Não | J7: 2026-10-04 | K7: Abrir vaga | L7: Freelance Writer Our organization is seeking content writers to create articles and blog posts on a variety of topics. The rate of pay is $20 per 100 words (this comes out to approximately $100 per article or $50 per hour). Some topics you may be asked to write about include the following (you can always turn down a topic if you do not feel comfortable writing about it, however if you have experience or expertise in a specific area, please let us know): Health & beauty Fitness Home Decor Fashion Sports Do it yourself Finance Legal Medical Family/Parenting Relationships Real Estate Restaurants Contracting (plumbing, pool building, remodeling, etc.) These are just some of the more general industries and topics that we cover. Requirements : We ask that all work be completed using a word processor such as Microsoft Word or Open Office A reliable internet connection and the ability to meet deadlines Good communication skills and respond in a timely manner to editorial staff when they ask for updates on tasks, etc Work well as a team member with the rest of our content management and editorial staff Note : Applicants to this job signaled that accessing some writing tasks may require payment. | M7: 💼 Freelance Writer 🏢 IAPWE 📍 Worldwide · Remoto 🎯 Advanced/Expert Our organization is seeking content writers to create articles and blog posts on a variety of topics. The rate of pay is $20 per 100 words (this comes out to approximately $100 per article or $50 per hour). 🔗 Candidate-se: https://remotive.com/remote-jobs/writing/freelance-writer-1185979 Fonte: Remotive #Vagas #TalentLab
A8: Freelance Copywriter | B8: Coalition Technologies | C8: Remotive | D8: Worldwide | E8: Não identificado | F8: Remoto | G8: Leadership | H8: Não identificado | I8: Não | J8: 2026-10-02 | K8: Abrir vaga | L8: Freelance Copywriter CT Marketing Agency is seeking skilled Freelance Copywriters to write high-quality, SEO-driven content for eCommerce and lead generation websites. This is a freelance, project-based writing role. The ideal candidate has excellent English writing skills, strong research ability, and experience writing content that follows detailed, client-specific guidelines. Projects commonly include category pages, product descriptions, blog posts, SEO landing pages, and website copy. About the Role Our client base is constantly evolving, and writers may create content across a wide range of industries, including: Fashion, including mass-market and luxury brands Skincare and beauty Tech and software Finance and investing Law, including family law, divorce, and product liability Education Home improvement Automobiles and motorcycles Health and wellness Medical and clinical fields Digital marketing SEO, PR, advertising, and marketing Writers with experience in highly specialized industries such as tech, finance, law, health, medical, SEO, PR, advertising, or marketing are strongly encouraged to apply. Responsibilities Write clear, engaging, SEO-friendly content for eCommerce and lead generation websites Create category pages, product descriptions, blog posts, landing pages, and website copy Research client industries, products, services, audiences, and competitors Follow detailed client guidelines and adapt to different brand voices Blend SEO best practices with brand priorities and conversion-focused writing Complete assignments by deadline and communicate professionally with the team Qualifications Excellent English writing, grammar, editing, and proofreading skills 2 to 4 years of professional, non-academic writing experience preferred Strong understanding of SEO writing best practices Ability to research unfamiliar industries and technical topics Ability to write creative, engaging, accurate, and ROI-focused content Portfolio featuring published work prefe... | M8: 💼 Freelance Copywriter 🏢 Coalition Technologies 📍 Worldwide · Remoto 🎯 Leadership CT Marketing Agency is seeking skilled Freelance Copywriters to write high-quality, SEO-driven content for eCommerce and lead generation websites. This is a freelance, project-based writing role. 🔗 Candidate-se: https://remotive.com/remote-jobs/writing/freelance-copywriter-1749306 Fonte: Remotive #Vagas #TalentLab
A9: Senior React Full-stack Developer | B9: Lemon.io | C9: Remotive | D9: Europe, USA, Canada, APAC | E9: Não identificado | F9: Remoto | G9: Professional/Experienced | H9: Cloud & Infraestrutura, Creative Tech, Dados, Dev, IA, Tech Business & Liderança | I9: Não | J9: 2026-10-02 | K9: Abrir vaga | L9: Senior React Full-stack Developer Are you a talented Senior Developer looking for a remote job that lets you show your skills and get decent compensation? Look no further than Lemon.io — the marketplace that connects you with hand-picked startups in the US and Europe. What we offer: The rate depends on your seniority level, skills and experience. We've already paid out over $11M to our engineers. No more hunting for clients or negotiating rates — let us handle the business side of things so you can focus on what you do best. We'll manually find the best project for you according to your skills and preferences. Choose a schedule that works best for you. It’s possible to communicate async or minimally overlap within team working hours. We respect your seniority so you can expect no micromanagement or screen trackers. Communicate directly with the clients. Most of them have technical backgrounds. Sounds good, yeah? We will support you from the time you submit the application throughout all cooperation stages. Most of our projects involve working in a fast-paced startup environment. We hope you like it as much as we do. Requirements for the Senior React & Python Position: 4+ years of software development experience. Commercial experience: React.js 3+ years & Python 3+ years OR React.js 2+ years & Python 5+ years OR React.js 5+ years & Python 2+ years Experience with AWS, GCP, or Azure is required. Other requirements: Strong technical skills: as a Senior Developer, you are expected to be able to create projects from scratch and have a deep understanding of application architecture. Clear and effective communication in English — advanced ability to discuss business tasks, justify decisions, and communicate issues. Good self-presentation is also essential for upcoming client calls. Strong self-organizational skills — ability to work full-time remotely with no supervision. Reliability — we want to trust you and expect that you won’t let us and the client down. Adaptabili... | M9: 💼 Senior React Full-stack Developer 🏢 Lemon.io 📍 Europe, USA, Canada, APAC · Remoto 🎯 Professional/Experienced 🧩 Área: Cloud & Infraestrutura, Creative Tech, Dados, Dev, IA, Tech Business & Liderança Are you a talented Senior Developer looking for a remote job that lets you show your skills and get decent compensation? Look no further than Lemon.io — the marketplace that connects you with hand-picked startups in the US and Europe. What we offer: The rate depends on your seniority level, skills and experience. 🔗 Candidate-se: https://remotive.com/remote-jobs/software-development/senior-react-full-stack-developer-2091133 Fonte: Remotive #Vagas #TalentLab #Cloud #UXDesign #Dados #Desenvolvimento #InteligenciaArtificial #GestaoDeTI
A10: Senior back-end Engineer | B10: Lemon.io | C10: Remotive | D10: Europe, USA, UK, Canada, Australia, Ireland, Switzerland, Singapore, Mexico, Iceland, Norway | E10: Não identificado | F10: Remoto | G10: Professional/Experienced | H10: Cloud & Infraestrutura, Creative Tech, Dados, Dev, IA, Tech Business & Liderança | I10: Não | J10: 2026-09-30 | K10: Abrir vaga | L10: Senior back-end Engineer Senior Developer? Work Remote. Get Paid Well. Build What Matters. Lemon.io connects hand-picked senior developers with vetted startups across the US and Europe — no bidding wars, no ghosting, just serious opportunities. We're currently hiring for a research-driven AI company on a mission to slash the cost of modern AI — co-designing hardware, software, algorithms, and models to make AI's benefits accessible to everyone. They're active open-source contributors, building the infrastructure behind next-generation AI at scale. Open roles: Senior Back-end Engineer (Golang), Senior DevOps Engineer, Senior Site Reliability Engineer, Senior Storage Engineer, Senior Python & LLM Developer, Senior Back-end Engineer (Python) Why this one's worth a look: You'll be working on infrastructure that directly shapes how AI gets built and deployed, at a company operating at the frontier of the field. Locations: the UK, Singapore, the US, and Canada. Requirements for Senior Back-end Developers: 5+ years of software development experience 3+ years of experience with Golang and/or Python 2+ years of experience with Kubernetes 2+ years of experience with AI agent development Not your stack? We're placing Senior Developers (4+ yrs commercial experience) across AI Agent Architecture, AI Automation Architecture, AI Engineering, Site Reliability Engineering, Platform Engineering, React & Python, React & Golang, Golang, React & Java, React & Ruby, Ruby, PHP & Vue, Vue & Node.js, React & .NET, Android & iOS, iOS & Swift, Flutter & Firebase, Solutions Engineer, Blockchain (Ethereum/Ethers.js/Wagmi/Viem/Solana), Angular & Node.js, Vue & .NET, Python & Vue, DevOps, MLOps, Data Science, Angular & PHP, Angular & .NET, Symfony & React, Symfony & Vue, Symfony & Angular, Python, Symfony & JavaScript & Next.js & TypeScript, Data Analysis, React & PHP, Data Engineering, Project Management, Product Management, QA Automation, QA Manual, Embedded Software Engineering, React Nativ... | M10: 💼 Senior back-end Engineer 🏢 Lemon.io 📍 Europe, USA, UK, Canada, Australia, Ireland, Switzerland, Singapore, Mexico, Iceland, Norway · Remoto 🎯 Professional/Experienced 🧩 Área: Cloud & Infraestrutura, Creative Tech, Dados, Dev, IA, Tech Business & Liderança Senior Developer? Work Remote. Get Paid Well. Build What Matters. Lemon.io connects hand-picked senior developers with vetted startups across the US and Europe — no bidding wars, no ghosting, just serious opportunities. 🔗 Candidate-se: https://remotive.com/remote-jobs/software-development/senior-back-end-engineer-2091132 Fonte: Remotive #Vagas #TalentLab #Cloud #UXDesign #Dados #Desenvolvimento #InteligenciaArtificial #GestaoDeTI
A11: Content Reviewer - United States | B11: TELUS Digital | C11: Remotive | D11: USA | E11: Meio período | F11: Remoto | G11: Não identificado | H11: IA | I11: Não | J11: 2026-09-21 | K11: Abrir vaga | L11: Content Reviewer - United States We are looking for an independent, flexible, remote opportunity where you can help improve AI-powered search technology from the comfort of your home? If you're curious, internet-savvy, and enjoy evaluating online content, this freelance project could be a great fit. A Day in the Life of a Content Reviewer - US In this role, you will analyze and provide feedback on text, webpages, images, and other types of online content for leading search engines using a specialized online platform. By reviewing and rating search results for relevance and quality, you will help improve the overall search experience for millions of users around the world, including yourself. Join our global community and put your skills to work supporting one of the world's leading search technologies. Service Rates The rate of pay is $0.2333 per completed task, with an estimated earning potential of $14 per hour. Compensation is based on tasks completed and project availability. Estimated earnings may vary depending on task volume and program requirements including, quality, and productivity, in accordance with the program's quality standards and guidelines. Please note that only one member per household may participate in this program. If it is identified that more than one person from the same household is participating in the TELUS Digital Rating Program, all associated accounts may be removed from the program. Independent Contractor Relationship This opportunity is offered on an independent contractor basis. Contributors have the flexibility to choose when and how much they work, subject to project availability and quality requirements. This opportunity is not and should not be construed as creating an employment relationship with TELUS Digital. Qualification path Qualification Process No previous professional experience is required to apply for this opportunity. However, participation in this project requires meeting the basic requirements and successfully ... | M11: 💼 Content Reviewer - United States 🏢 TELUS Digital 📍 USA · Remoto 📄 Meio período 🧩 Área: IA We are looking for an independent, flexible, remote opportunity where you can help improve AI-powered search technology from the comfort of your home? If you're curious, internet-savvy, and enjoy evaluating online content, this freelance project could be a great fit. 🔗 Candidate-se: https://remotive.com/remote-jobs/all-others/content-reviewer-united-states-2091144 Fonte: Remotive #Vagas #TalentLab #InteligenciaArtificial
A12: Clinical Data Manager | B12: Penumbra | C12: RemoteOK | D12: Your Remote US Home Office | E12: Temporário | F12: Remoto | G12: Leadership | H12: Tech Business & Liderança | I12: Não | J12: 2026-10-21 | K12: Abrir vaga | L12: Clinical Data Manager General Summary The temporary Clinical Data Manager acts as a lead data manager for one or more projects, applies data management experience to clinical trials, and utilizes functional knowledge of the logistics of clinical trials to ensure the quality and integrity of clinical trial data. The CDM works on multi-functional teams and supports clinical trial projects as a departmental subject matter expert (SME). We are seeking a temporary clinical data manager who can dedicate 20 hours a week to support ongoing study activities. The initial assignment is for 6 months, but may be extended to meet the needs of our Team. Applicants must be eligible to live and work in the US. Specific Duties and Responsibilities â¢Independently lead and/or perform all data management activities within an assigned study (e.g., study startup, study conduct, study closeout, and reporting). * â¢Serve as the data management SME on multidisciplinary project teams providing specific expertise on timeline development, identification of data management deliverables and resource requirements. * â¢Participate in the creation, review, and maintenance of project timelines and monitor progress of data management activities. * â¢Provide oversight for Data Management CRO and other vendors to ensure compliance with the protocol, external/internal standards, Good Clinical Practices (GCPs), applicable regulatory guidelines, SOPs, and other relevant guidelines. â¢Ensure Data Management documentation is filed/archived according to applicable Penumbra and regulatory requirements. * â¢Interact with data management, biostatistics, Clinical Affairs and Medical Affairs team to ensure integrity and quality of data. * â¢Contribute ideas to the development of the department, identifying areas for improvement (e.g., SOPs, processes) â¢Participates in audits and inspections. * â¢Attend Investigator Meetings when requested to provide training on CRF data completion. â¢Responsible for... | M12: 💼 Clinical Data Manager 🏢 Penumbra 📍 Your Remote US Home Office · Remoto 📄 Temporário 🎯 Leadership 🧩 Área: Tech Business & Liderança General Summary The temporary Clinical Data Manager acts as a lead data manager for one or more projects, applies data management experience to clinical trials, and utilizes functional knowledge of the logistics of clinical trials to ensure the quality and integrity of clinical trial data. 🔗 Candidate-se: https://remoteOK.com/remote-jobs/remote-clinical-data-manager-penumbra-1137550 Fonte: RemoteOK #Vagas #TalentLab #GestaoDeTI
... A31: Staff Software Development Engineer SDM | B31: Delinea | C31: RemoteOK | D31: Redwood City | E31: Não identificado | F31: Remoto | G31: Advanced/Expert | H31: Cloud & Infraestrutura, Dev, IA, Tech Business & Liderança | I31: Não | J31: 2026-08-16 | K31: Abrir vaga | L31: Staff Software Development Engineer SDM About Delinea: Delinea is a pioneer in securing human and machine identities through intelligent, centralized authorization, empowering organizations to seamlessly govern their interactions across the modern enterprise. Leveraging AI-powered intelligence, Delineaâs leading cloud-native Identity Security Platform applies context throughout the entire identity lifecycle â across cloud and traditional infrastructure, data, SaaS applications, and AI. It is the only platform that enables you to discover all identities â including workforce, IT administrator, developers, and machines â assign appropriate access levels, detect irregularities, and respond to threats in real-time. With deployment in weeks, not months, 90% fewer resources to manage than the nearest competitor, and a 99.995% uptime, Delinea delivers robust security and operational efficiency without compromise. Learn more about Delinea on Delinea.com , LinkedIn , X , and YouTube . Join our passionate, global team at Delinea and help us make the world a safer and more secure place. Our success is driven by world-class product leadership, outstanding engineers, and strategic investment from TPG. We value diversity, innovation, and a culture of respect and fairness. If you're ready to push boundaries and challenge the status quo in security, we want to hear from you. Â Apply today to help us achieve our mission. Job Summary This position is on the team building StrongDM, now part of Delineaâthe universal access management platform that secures and audits access to databases, servers, Kubernetes clusters, and web applications. As a Staff Software Engineer, you will apply deep expertise across distributed systems, security, and cloud architecture to help shape the technical direction of StrongDMâs proxy and control-plane platform. You will take on the platformâs most complex and ambiguous engineering challenges, exercise independent judgment on architecture a... | M31: 💼 Staff Software Development Engineer SDM 🏢 Delinea 📍 Redwood City · Remoto 🎯 Advanced/Expert 🧩 Área: Cloud & Infraestrutura, Dev, IA, Tech Business & Liderança About Delinea: Delinea is a pioneer in securing human and machine identities through intelligent, centralized authorization, empowering organizations to seamlessly govern their interactions across the modern enterprise. 🔗 Candidate-se: https://remoteOK.com/remote-jobs/remote-staff-software-development-engineer-sdm-delinea-1136796 Fonte: RemoteOK #Vagas #TalentLab #Cloud #Desenvolvimento #InteligenciaArtificial #GestaoDeTI

Sheet Resumo
A1: Resumo das vagas coletadas
A2: Gerado em 22/10/2026 11:34 | termos: estágio tecnologia, desenvolvedor, dados, segurança da informação, inteligência artificial, cloud, devops, ux design, robótica, gestão de ti
A4: Total de vagas | B4: =COUNTA(Vagas!A2:A31)
A5: Vagas afirmativas | B5: =COUNTIF(Vagas!I2:I31,"Sim")
A7: Por cluster | B7: Vagas
A8: Cyber | B8: =SUMPRODUCT(--ISNUMBER(SEARCH("|"&A8&"|","|"&SUBSTITUTE(Vagas!$H$2:$H$31,", ","|")&"|")))
A9: IA | B9: =SUMPRODUCT(--ISNUMBER(SEARCH("|"&A9&"|","|"&SUBSTITUTE(Vagas!$H$2:$H$31,", ","|")&"|")))
A10: Dados | B10: =SUMPRODUCT(--ISNUMBER(SEARCH("|"&A10&"|","|"&SUBSTITUTE(Vagas!$H$2:$H$31,", ","|")&"|")))
A11: Dev | B11: =SUMPRODUCT(--ISNUMBER(SEARCH("|"&A11&"|","|"&SUBSTITUTE(Vagas!$H$2:$H$31,", ","|")&"|")))
A12: Cloud & Infraestrutura | B12: =SUMPRODUCT(--ISNUMBER(SEARCH("|"&A12&"|","|"&SUBSTITUTE(Vagas!$H$2:$H$31,", ","|")&"|")))
A13: Creative Tech | B13: =SUMPRODUCT(--ISNUMBER(SEARCH("|"&A13&"|","|"&SUBSTITUTE(Vagas!$H$2:$H$31,", ","|")&"|")))
A14: Robotics & Systems | B14: =SUMPRODUCT(--ISNUMBER(SEARCH("|"&A14&"|","|"&SUBSTITUTE(Vagas!$H$2:$H$31,", ","|")&"|")))
A15: Tech Business & Liderança | B15: =SUMPRODUCT(--ISNUMBER(SEARCH("|"&A15&"|","|"&SUBSTITUTE(Vagas!$H$2:$H$31,", ","|")&"|")))
A17: Por tipo de contratação | B17: Vagas
A18: Estágio | B18: =SUMPRODUCT(--ISNUMBER(SEARCH("|"&A18&"|","|"&SUBSTITUTE(Vagas!$E$2:$E$31,", ","|")&"|")))
A19: Trainee | B19: =SUMPRODUCT(--ISNUMBER(SEARCH("|"&A19&"|","|"&SUBSTITUTE(Vagas!$E$2:$E$31,", ","|")&"|")))
A20: Jovem Aprendiz | B20: =SUMPRODUCT(--ISNUMBER(SEARCH("|"&A20&"|","|"&SUBSTITUTE(Vagas!$E$2:$E$31,", ","|")&"|")))
A21: Emprego (CLT) | B21: =SUMPRODUCT(--ISNUMBER(SEARCH("|"&A21&"|","|"&SUBSTITUTE(Vagas!$E$2:$E$31,", ","|")&"|")))
A22: Pessoa Jurídica (PJ) | B22: =SUMPRODUCT(--ISNUMBER(SEARCH("|"&A22&"|","|"&SUBSTITUTE(Vagas!$E$2:$E$31,", ","|")&"|")))
A23: Temporário | B23: =SUMPRODUCT(--ISNUMBER(SEARCH("|"&A23&"|","|"&SUBSTITUTE(Vagas!$E$2:$E$31,", ","|")&"|")))
A24: Meio período | B24: =SUMPRODUCT(--ISNUMBER(SEARCH("|"&A24&"|","|"&SUBSTITUTE(Vagas!$E$2:$E$31,", ","|")&"|")))
A25: Voluntariado | B25: =SUMPRODUCT(--ISNUMBER(SEARCH("|"&A25&"|","|"&SUBSTITUTE(Vagas!$E$2:$E$31,", ","|")&"|")))
A27: Por modelo de trabalho | B27: Vagas
A28: Remoto | B28: =SUMPRODUCT(--ISNUMBER(SEARCH("|"&A28&"|","|"&SUBSTITUTE(Vagas!$F$2:$F$31,", ","|")&"|")))
A29: Híbrido | B29: =SUMPRODUCT(--ISNUMBER(SEARCH("|"&A29&"|","|"&SUBSTITUTE(Vagas!$F$2:$F$31,", ","|")&"|")))
A30: No local | B30: =SUMPRODUCT(--ISNUMBER(SEARCH("|"&A30&"|","|"&SUBSTITUTE(Vagas!$F$2:$F$31,", ","|")&"|")))
A32: Por nível | B32: Vagas
A33: Early Career | B33: =SUMPRODUCT(--ISNUMBER(SEARCH("|"&A33&"|","|"&SUBSTITUTE(Vagas!$G$2:$G$31,", ","|")&"|")))
A34: Professional/Experienced | B34: =SUMPRODUCT(--ISNUMBER(SEARCH("|"&A34&"|","|"&SUBSTITUTE(Vagas!$G$2:$G$31,", ","|")&"|")))
A35: Advanced/Expert | B35: =SUMPRODUCT(--ISNUMBER(SEARCH("|"&A35&"|","|"&SUBSTITUTE(Vagas!$G$2:$G$31,", ","|")&"|")))
A36: Leadership | B36: =SUMPRODUCT(--ISNUMBER(SEARCH("|"&A36&"|","|"&SUBSTITUTE(Vagas!$G$2:$G$31,", ","|")&"|")))
A38: Por fonte | B38: Vagas
A39: RemoteOK | B39: =COUNTIF(Vagas!$C$2:$C$31,A39)
A40: Remotive | B40: =COUNTIF(Vagas!$C$2:$C$31,A40)
